status/__init__.py
status/app.py
status/settings.py
status/commands/__init__.py
status/commands/help.py
status/commands/http_request.py
status/commands/usage.py
status/commands/version.py
status-0.2.4.data/scripts/status
status-0.2.4.dist-info/DESCRIPTION.rst
status-0.2.4.dist-info/entry_points.txt
status-0.2.4.dist-info/METADATA
status-0.2.4.dist-info/pydist.json
status-0.2.4.dist-info/RECORD
status-0.2.4.dist-info/top_level.txt
status-0.2.4.dist-info/WHEEL
